metal_shredding_center/__init__.py
metal_shredding_center/drive info.s.HTML
metal_shredding_center/module.s.HTML
metal_shredding_center/notices.s.HTML
metal_shredding_center/tutorial.S.HTML
metal_shredding_center/___itinerary/itinerary.S.HTML
metal_shredding_center/_license/license.s.HTML
metal_shredding_center/_status/status.S.HTML
metal_shredding_center/_status/status.proc.py
metal_shredding_center/_status/status/status_1.py
metal_shredding_center/_status/status/status_2_start_scan_and_sculpt.py
metal_shredding_center/_status/status/status_3_end_of_drive_scans.py
metal_shredding_center/_status/status/status_4_end_scan_and_sculpt.py
metal_shredding_center/_status/status/status_5_status_scan.py
metal_shredding_center/_status/status/status_6_after_end_of_drive_sculpt.py
metal_shredding_center/_status/status/erase/status_1.py
metal_shredding_center/_status/status_advanced/advanced_status_1_entire_drive.py
metal_shredding_center/_status/status_advanced/advanced_status_2_entire_drive_erase.py
metal_shredding_center/_status/status_shell/s1/flask_server.py
metal_shredding_center/_status/status_shell/s1/status_1.py
metal_shredding_center/clique/__init__.py
metal_shredding_center/clique/_status/status_1.py
metal_shredding_center/decor/__init__.py
metal_shredding_center/erase/__init__.py
metal_shredding_center/erase/clique.py
metal_shredding_center/modules/LS_BLK/__init__.py
metal_shredding_center/modules/LS_BLK/calc_size.py
metal_shredding_center/modules/repair/repair.s.HTML
metal_shredding_center/scan/__init__.py
metal_shredding_center/scan/can_scan.py
metal_shredding_center/scan/clique.py
metal_shredding_center/scan/is_last_byte.py
metal_shredding_center/scan/scan.s.HTML
metal_shredding_center/scan/similar techs.s.HTML
metal_shredding_center/sculpt/__init__.py
metal_shredding_center/sculpt/clique.py
metal_shredding_center/sculpt/sculpt.s.HTML
metal_shredding_center/sculpt/strategies/patterns.s.HTML
metal_shredding_center/sculpt/strategies/strategy_1.py
metal_shredding_center-1.0.1.dist-info/METADATA
metal_shredding_center-1.0.1.dist-info/WHEEL
metal_shredding_center-1.0.1.dist-info/top_level.txt
metal_shredding_center-1.0.1.dist-info/RECORD
