Metadata-Version: 2.1
Name: metal_shredding_center
Version: 1.0.1
License: CL
Requires-Dist: volts
Requires-Dist: shares
Requires-Dist: ships
Requires-Dist: flask
Requires-Dist: jsonschema
Requires-Dist: rich
